{
  "WORLD_COORD_BITS": 13,
  "QUADRANT_COORD_BITS": 5,
  "PAINT_ID_BITS": 16,
  "NAME": "decorations",
  "SPAWN_PLACE_PAINT_ID": 0,
  "PAINT_COUNT": 5,
  "PAINT_INSTANCE_COUNT": 48,
  "PAINT_NAMES": [
    "spawn_place",
    "jump",
    "rightarrow",
    "leftarrow",
    "oil"
  ],
  "PAINTS": [
    0,
    894,
    190,
    68,
    102,
    0,
    1,
    35,
    290,
    205,
    140,
    0,
    2,
    188,
    144,
    68,
    100,
    0,
    3,
    120,
    152,
    68,
    96,
    0,
    4,
    263,
    143,
    114,
    99,
    0
  ],
  "PAINT_INSTANCES": [
    1,
    448,
    6022,
    180,
    1.5,
    1.5,
    1,
    805,
    1922,
    180,
    1.5,
    1.5,
    1,
    5534,
    813,
    -90,
    1.5,
    1.5,
    1,
    5534,
    478,
    -90,
    1.5,
    1.5,
    1,
    463,
    1924,
    180,
    1.5,
    1.5,
    1,
    810,
    6026,
    180,
    1.5,
    1.5,
    1,
    3962,
    6445,
    90,
    1.5,
    1.5,
    1,
    3968,
    6110,
    90,
    1.5,
    1.5,
    2,
    5954,
    2187,
    0,
    1.54,
    2.55,
    2,
    1526,
    2760,
    0,
    1.54,
    2.55,
    2,
    1601,
    2268,
    0,
    1.86,
    2.55,
    2,
    2925,
    2657,
    0,
    1.5,
    2.55,
    2,
    5539,
    3650,
    90,
    1.55,
    2.54,
    2,
    3338,
    2160,
    90,
    1.55,
    2.54,
    2,
    6339,
    2503,
    -90,
    1.55,
    2.54,
    2,
    5050,
    6348,
    90,
    1.55,
    2.54,
    2,
    2016,
    7016,
    0,
    1.54,
    2.55,
    2,
    6069,
    3864,
    180,
    1.54,
    2.55,
    2,
    6728,
    6298,
    0,
    1.54,
    2.55,
    3,
    7466,
    1361,
    0,
    1.5,
    2.5,
    3,
    1451,
    7380,
    90,
    1.5,
    2.5,
    3,
    772,
    6935,
    -180,
    1.5,
    2.5,
    3,
    728,
    6461,
    -180,
    1.5,
    2.5,
    3,
    1169,
    4949,
    -105,
    1.5,
    2.5,
    3,
    1748,
    4780,
    -90,
    1.5,
    2.5,
    3,
    789,
    3133,
    -180,
    1.5,
    2.5,
    3,
    1492,
    720,
    -90,
    1.5,
    2.5,
    3,
    718,
    2239,
    -180,
    1.5,
    2.5,
    3,
    752,
    2687,
    -180,
    1.5,
    2.5,
    3,
    2880,
    618,
    -90,
    1.5,
    2.5,
    3,
    6867,
    1815,
    90,
    1.5,
    2.5,
    3,
    2112,
    657,
    -90,
    1.5,
    2.5,
    3,
    1039,
    927,
    -120,
    1.5,
    2.5,
    3,
    2329,
    2621,
    180,
    1.5,
    2.5,
    3,
    2395,
    4661,
    -90,
    1.5,
    2.5,
    3,
    7238,
    3471,
    0,
    1.5,
    2.5,
    3,
    7629,
    5076,
    0,
    1.5,
    2.5,
    3,
    7227,
    5583,
    90,
    1.5,
    2.5,
    3,
    6296,
    7142,
    90,
    1.5,
    2.5,
    4,
    1501,
    4818,
    60,
    1.5,
    1.5,
    4,
    5911,
    3606,
    45,
    1.5,
    1.5,
    4,
    4975,
    542,
    -30,
    1.5,
    1.5,
    4,
    2328,
    2216,
    -45,
    1.5,
    1.5,
    4,
    761,
    2477,
    0,
    1.5,
    1.5,
    4,
    2671,
    6371,
    0,
    1.5,
    1.5,
    4,
    6532,
    1807,
    0,
    1.5,
    1.5,
    4,
    5640,
    6354,
    45,
    1.5,
    1.5,
    4,
    7315,
    3983,
    -15,
    1.6,
    1.6
  ]
}